anonymize_script.py
anonymize/__init__.py
anonymize/io.py
anonymize-0.5.dist-info/DESCRIPTION.rst
anonymize-0.5.dist-info/METADATA
anonymize-0.5.dist-info/RECORD
anonymize-0.5.dist-info/WHEEL
anonymize-0.5.dist-info/entry_points.txt
anonymize-0.5.dist-info/metadata.json
anonymize-0.5.dist-info/top_level.txt
examples/basic_test.py
examples/sample_schema.json
examples/test_input.csv
