Metadata-Version: 2.0
Name: anonymize
Version: 0.5
Summary: Simple yet efficient data anonymization framework
Home-page: https://github.com/MichalZylinski/anonymize
Author: Michal Zylinski
Author-email: michal.zylinski@gmail.com
License: MIT
Platform: UNKNOWN
Classifier: Programming Language :: Python :: 2.7
Classifier: Programming Language :: Python :: 3
